google/cloud/texttospeech/__init__.py
google/cloud/texttospeech/gapic_version.py
google/cloud/texttospeech/py.typed
google/cloud/texttospeech_v1/__init__.py
google/cloud/texttospeech_v1/gapic_metadata.json
google/cloud/texttospeech_v1/gapic_version.py
google/cloud/texttospeech_v1/py.typed
google/cloud/texttospeech_v1/services/__init__.py
google/cloud/texttospeech_v1/services/text_to_speech/__init__.py
google/cloud/texttospeech_v1/services/text_to_speech/async_client.py
google/cloud/texttospeech_v1/services/text_to_speech/client.py
google/cloud/texttospeech_v1/services/text_to_speech/transports/__init__.py
google/cloud/texttospeech_v1/services/text_to_speech/transports/base.py
google/cloud/texttospeech_v1/services/text_to_speech/transports/grpc.py
google/cloud/texttospeech_v1/services/text_to_speech/transports/grpc_asyncio.py
google/cloud/texttospeech_v1/services/text_to_speech/transports/rest.py
google/cloud/texttospeech_v1/services/text_to_speech/transports/rest_base.py
google/cloud/texttospeech_v1/services/text_to_speech_long_audio_synthesize/__init__.py
google/cloud/texttospeech_v1/services/text_to_speech_long_audio_synthesize/async_client.py
google/cloud/texttospeech_v1/services/text_to_speech_long_audio_synthesize/client.py
google/cloud/texttospeech_v1/services/text_to_speech_long_audio_synthesize/transports/__init__.py
google/cloud/texttospeech_v1/services/text_to_speech_long_audio_synthesize/transports/base.py
google/cloud/texttospeech_v1/services/text_to_speech_long_audio_synthesize/transports/grpc.py
google/cloud/texttospeech_v1/services/text_to_speech_long_audio_synthesize/transports/grpc_asyncio.py
google/cloud/texttospeech_v1/services/text_to_speech_long_audio_synthesize/transports/rest.py
google/cloud/texttospeech_v1/services/text_to_speech_long_audio_synthesize/transports/rest_base.py
google/cloud/texttospeech_v1/types/__init__.py
google/cloud/texttospeech_v1/types/cloud_tts.py
google/cloud/texttospeech_v1/types/cloud_tts_lrs.py
google_cloud_texttospeech-2.27.0.dist-info/LICENSE
google_cloud_texttospeech-2.27.0.dist-info/METADATA
google_cloud_texttospeech-2.27.0.dist-info/WHEEL
google_cloud_texttospeech-2.27.0.dist-info/top_level.txt
google_cloud_texttospeech-2.27.0.dist-info/RECORD
